pam/__init__.py
pam/__internals.py
pam/pam.py
pam/version.py
python_pam-2.0.0.dist-info/LICENSE
python_pam-2.0.0.dist-info/METADATA
python_pam-2.0.0.dist-info/WHEEL
python_pam-2.0.0.dist-info/top_level.txt
python_pam-2.0.0.dist-info/RECORD
