Metadata-Version: 2.1
Name: python-pam
Version: 2.0.0
Summary: Python PAM module using ctypes, py3
Home-page: https://github.com/FirefighterBlu3/python-pam
Author: David Ford
Author-email: david@blue-labs.org
License: License :: OSI Approved :: MIT License
Project-URL: Bug Tracker, https://github.com/FirefighterBlu3/python-pam/issues
Platform: UNKNOWN
Classifier: Development Status :: 6 - Mature
Classifier: Environment :: Plugins
Classifier: Intended Audience :: Developers
Classifier: Intended Audience :: Information Technology
Classifier: Intended Audience :: System Administrators
Classifier: License :: OSI Approved :: MIT License
Classifier: Operating System :: POSIX
Classifier: Operating System :: POSIX :: Linux
Classifier: Programming Language :: Python
Classifier: Programming Language :: Python :: 2
Classifier: Programming Language :: Python :: 3
Classifier: Topic :: Security
Classifier: Topic :: System :: Systems Administration :: Authentication/Directory
License-File: LICENSE
